surrealdantic/__init__.py
surrealdantic/_db.py
surrealdantic/controller.py
surrealdantic/events.py
surrealdantic/model.py
surrealdantic/repository.py
surrealdantic/utils.py
surrealdantic/vector.py
surrealdantic-0.0.1.dist-info/METADATA
surrealdantic-0.0.1.dist-info/WHEEL
surrealdantic-0.0.1.dist-info/RECORD
