Metadata-Version: 2.1
Name: surrealdantic
Version: 0.0.1
Summary: 
Author: obahamonde
Author-email: oscarmartinbahamondemunoz@gmail.com
Requires-Python: >=3.10,<4.0
Classifier: Programming Language :: Python :: 3
Classifier: Programming Language :: Python :: 3.10
Classifier: Programming Language :: Python :: 3.11
Classifier: Programming Language :: Python :: 3.12
Requires-Dist: fastapi (>=0.108.0,<0.109.0)
Requires-Dist: numpy (>=1.26.3,<2.0.0)
Requires-Dist: rich (>=13.7.0,<14.0.0)
Requires-Dist: sse-starlette (>=1.8.2,<2.0.0)
Requires-Dist: surrealdb (>=0.3.2,<0.4.0)
Requires-Dist: tenacity (>=8.2.3,<9.0.0)
